{
  "metadata": {
    "lastUpdated": "2026-06-17T18:04:20.510477+00:00",
    "source": "Generated locally from Excel LiveStandings, LiveThirdPlace, and MatchResults sheets",
    "sourceWorkbook": "C:\\Users\\kevin\\OneDrive - Mass General Brigham\\world_cup_2026_group_stage_challenge_MPEC_vCurrent.xlsx",
    "completedGroups": [
      "A",
      "D",
      "E",
      "I",
      "J",
      "K",
      "L"
    ],
    "thirdPlaceScoringActive": true,
    "playedMatches": 24,
    "totalMatches": 72,
    "goalsSoFar": 71,
    "actualGroupStageGoals": null
  },
  "groupStandings": {
    "A": [
      "Mexico",
      "South Korea",
      "Czech Republic",
      "South Africa"
    ],
    "B": [],
    "C": [],
    "D": [
      "United States",
      "Australia",
      "Türkiye",
      "Paraguay"
    ],
    "E": [
      "Germany",
      "Ivory Coast",
      "Ecuador",
      "Curaçao"
    ],
    "F": [],
    "G": [],
    "H": [],
    "I": [
      "Norway",
      "France",
      "Senegal",
      "Iraq"
    ],
    "J": [
      "Argentina",
      "Austria",
      "Jordan",
      "Algeria"
    ],
    "K": [
      "Colombia",
      "Portugal",
      "Congo DR",
      "Uzbekistan"
    ],
    "L": [
      "Ghana",
      "England",
      "Croatia",
      "Panama"
    ]
  },
  "thirdPlaceGroups": [
    "G",
    "H"
  ]
}